imr/__init__.py
imr/imr.py
imr/imr_cli.py
imr-0.0.1rc4.dist-info/LICENSE
imr-0.0.1rc4.dist-info/METADATA
imr-0.0.1rc4.dist-info/WHEEL
imr-0.0.1rc4.dist-info/entry_points.txt
imr-0.0.1rc4.dist-info/RECORD
